orangewire/__init__.py
orangewire/__main__.py
orangewire/discogs.py
orangewire/scraper.py
orangewire/yt.py
orangewire-1.0.1a1.dist-info/DESCRIPTION.rst
orangewire-1.0.1a1.dist-info/METADATA
orangewire-1.0.1a1.dist-info/RECORD
orangewire-1.0.1a1.dist-info/WHEEL
orangewire-1.0.1a1.dist-info/entry_points.txt
orangewire-1.0.1a1.dist-info/metadata.json
orangewire-1.0.1a1.dist-info/top_level.txt
