Metadata-Version: 2.0
Name: orangewire
Version: 1.0.1a1
Summary: Searches for, fetches, and correctly tags MP3s from YouTube
Home-page: https://github.com/zebradeltasavage/orangewire
Author: Zelly Snyder
Author-email: zds@zds.li
License: UNKNOWN
Keywords: mp3 audio youtube-dl id3
Platform: UNKNOWN
Classifier: Development Status :: 3 - Alpha
Classifier: Intended Audience :: Developers
Classifier: License :: OSI Approved :: GNU General Public License v3 or later (GPLv3+)
Classifier: Programming Language :: Python :: 3.5
Classifier: Programming Language :: Python :: 3.6
Requires-Dist: youtube-dl
Requires-Dist: beautifulsoup4
Requires-Dist: requests
Requires-Dist: mutagen
Requires-Dist: discogs-client
